lcbuilder/HarmonicSelector.py
lcbuilder/LcBuild.py
lcbuilder/__init__.py
lcbuilder/constants.py
lcbuilder/eleanor_manager.py
lcbuilder/helper.py
lcbuilder/lcbuilder_class.py
lcbuilder/curve_preparer/CurvePreparer.py
lcbuilder/curve_preparer/Flattener.py
lcbuilder/curve_preparer/__init__.py
lcbuilder/eleanor/__init__.py
lcbuilder/eleanor/crossmatch.py
lcbuilder/eleanor/eleanor.py
lcbuilder/eleanor/ffi.py
lcbuilder/eleanor/fill_grid.cpp
lcbuilder/eleanor/mast.py
lcbuilder/eleanor/maxsector.py
lcbuilder/eleanor/models.py
lcbuilder/eleanor/postcard.py
lcbuilder/eleanor/postcard_centers.txt
lcbuilder/eleanor/source.py
lcbuilder/eleanor/targetdata.py
lcbuilder/eleanor/update.py
lcbuilder/eleanor/utils.py
lcbuilder/eleanor/version.py
lcbuilder/eleanor/visualize.py
lcbuilder/eleanor/metadata/ffi.guide
lcbuilder/eleanor/tests/__init__.py
lcbuilder/eleanor/tests/test_ffi.py
lcbuilder/eleanor/tests/test_mast.py
lcbuilder/eleanor/tests/test_postcard.py
lcbuilder/eleanor/tests/test_source.py
lcbuilder/eleanor/tests/test_targetdata.py
lcbuilder/eleanor/tests/test_visualize.py
lcbuilder/objectinfo/InputObjectInfo.py
lcbuilder/objectinfo/InvalidNumberOfSectorsError.py
lcbuilder/objectinfo/MissionInputObjectInfo.py
lcbuilder/objectinfo/MissionObjectInfo.py
lcbuilder/objectinfo/ObjectInfo.py
lcbuilder/objectinfo/ObjectProcessingError.py
lcbuilder/objectinfo/__init__.py
lcbuilder/objectinfo/preparer/LightcurveBuilder.py
lcbuilder/objectinfo/preparer/MissionInputLightcurveBuilder.py
lcbuilder/objectinfo/preparer/MissionLightcurveBuilder.py
lcbuilder/objectinfo/preparer/__init__.py
lcbuilder/objectinfo/preparer/mission_data_preparer.py
lcbuilder/photometry/__init__.py
lcbuilder/photometry/aperture_extractor.py
lcbuilder/star/EpicStarCatalog.py
lcbuilder/star/HabitabilityCalculator.py
lcbuilder/star/KicStarCatalog.py
lcbuilder/star/StarCatalog.py
lcbuilder/star/TicStarCatalog.py
lcbuilder/star/__init__.py
lcbuilder/star/starinfo.py
lcbuilder/tests/__init__.py
lcbuilder-0.25.4.dist-info/LICENSE
lcbuilder-0.25.4.dist-info/METADATA
lcbuilder-0.25.4.dist-info/WHEEL
lcbuilder-0.25.4.dist-info/top_level.txt
lcbuilder-0.25.4.dist-info/RECORD
