Metadata-Version: 2.1
Name: lcbuilder
Version: 0.25.4
Summary: Easy light curve builder from multiple sources
Home-page: https://github.com/PlanetHunders/lcbuilder
Author: M. Dévora-Pajares
Author-email: mdevorapajares@protonmail.com
Classifier: Programming Language :: Python :: 3
Classifier: License :: OSI Approved :: MIT License
Classifier: Operating System :: OS Independent
Requires-Python: >=3.11
License-File: LICENSE
Requires-Dist: certifi==2025.1.31
Requires-Dist: Cython==3.0.6
Requires-Dist: everest-pipeline==2.0.12
Requires-Dist: pandas==2.2.3
Requires-Dist: lightkurve==2.5.0
Requires-Dist: matplotlib==3.10.1
Requires-Dist: photutils==2.2.0
Requires-Dist: pybind11==2.11.1
Requires-Dist: requests==2.32.3
Requires-Dist: tess-point==0.9.2
Requires-Dist: foldedleastsquares==1.1.11
Requires-Dist: typing-extensions==4.13.2
Requires-Dist: uncertainties==3.2.2
Requires-Dist: urllib3==2.4.0
Requires-Dist: wotan==1.9
